django_messages_to_bootstrap_notify-0.2.6.dist-info/DESCRIPTION.rst
django_messages_to_bootstrap_notify-0.2.6.dist-info/METADATA
django_messages_to_bootstrap_notify-0.2.6.dist-info/RECORD
django_messages_to_bootstrap_notify-0.2.6.dist-info/WHEEL
django_messages_to_bootstrap_notify-0.2.6.dist-info/metadata.json
django_messages_to_bootstrap_notify-0.2.6.dist-info/top_level.txt
dm2bn/__init__.py
dm2bn/apps.py
dm2bn/models.py
dm2bn/settings.py
dm2bn/static/dm2bn/vendor/bootstrap/LICENSE
dm2bn/static/dm2bn/vendor/bootstrap/css/bootstrap-theme.css
dm2bn/static/dm2bn/vendor/bootstrap/css/bootstrap-theme.css.map
dm2bn/static/dm2bn/vendor/bootstrap/css/bootstrap-theme.min.css
dm2bn/static/dm2bn/vendor/bootstrap/css/bootstrap-theme.min.css.map
dm2bn/static/dm2bn/vendor/bootstrap/css/bootstrap.css
dm2bn/static/dm2bn/vendor/bootstrap/css/bootstrap.css.map
dm2bn/static/dm2bn/vendor/bootstrap/css/bootstrap.min.css
dm2bn/static/dm2bn/vendor/bootstrap/css/bootstrap.min.css.map
dm2bn/static/dm2bn/vendor/bootstrap/fonts/glyphicons-halflings-regular.eot
dm2bn/static/dm2bn/vendor/bootstrap/fonts/glyphicons-halflings-regular.svg
dm2bn/static/dm2bn/vendor/bootstrap/fonts/glyphicons-halflings-regular.ttf
dm2bn/static/dm2bn/vendor/bootstrap/fonts/glyphicons-halflings-regular.woff
dm2bn/static/dm2bn/vendor/bootstrap/fonts/glyphicons-halflings-regular.woff2
dm2bn/static/dm2bn/vendor/bootstrap/js/bootstrap.js
dm2bn/static/dm2bn/vendor/bootstrap/js/bootstrap.min.js
dm2bn/static/dm2bn/vendor/bootstrap-notify/LICENSE.txt
dm2bn/static/dm2bn/vendor/bootstrap-notify/bootstrap-notify.js
dm2bn/static/dm2bn/vendor/bootstrap-notify/bootstrap-notify.min.js
dm2bn/static/dm2bn/vendor/bootstrap-notify-simple-wrapper/MIT-LICENSE
dm2bn/static/dm2bn/vendor/bootstrap-notify-simple-wrapper/bootstrap-notify-simple-wrapper.js
dm2bn/static/dm2bn/vendor/bootstrap-notify-simple-wrapper/bootstrap-notify-simple-wrapper.min.js
dm2bn/static/dm2bn/vendor/font-awesome/css/LICENSE
dm2bn/static/dm2bn/vendor/font-awesome/css/font-awesome.css
dm2bn/static/dm2bn/vendor/font-awesome/css/font-awesome.min.css
dm2bn/static/dm2bn/vendor/font-awesome/fonts/FontAwesome.otf
dm2bn/static/dm2bn/vendor/font-awesome/fonts/LICENSE.txt
dm2bn/static/dm2bn/vendor/font-awesome/fonts/fontawesome-webfont.eot
dm2bn/static/dm2bn/vendor/font-awesome/fonts/fontawesome-webfont.svg
