Metadata-Version: 2.0
Name: django-messages-to-bootstrap-notify
Version: 0.2.6
Summary: Show django messages using bootstrap-notify
Home-page: https://github.com/DCOD-OpenSource/django-messages-to-bootstrap-notify/
Author: Alexei Andrushievich
Author-email: vint21h@vint21h.pp.ua
License: MIT
Download-URL: https://github.com/DCOD-OpenSource/django-messages-to-bootstrap-notify/archive/0.2.6.tar.gz
Platform: UNKNOWN
Classifier: Environment :: Plugins
Classifier: License :: OSI Approved :: MIT License
Classifier: Operating System :: Unix
Classifier: Programming Language :: Python :: 2.7
Classifier: Programming Language :: Python :: 3
Classifier: Topic :: Utilities
Classifier: Framework :: Django :: 1.10
Classifier: Framework :: Django :: 1.11
Requires-Dist: Django
